igelfs/__init__.py
igelfs/cli.py
igelfs/constants.py
igelfs/convert.py
igelfs/crypto.py
igelfs/device.py
igelfs/filesystem.py
igelfs/fuse.py
igelfs/keys.py
igelfs/kml.py
igelfs/lxos.py
igelfs/registry.py
igelfs/reset.py
igelfs/utils.py
igelfs/wfs.py
igelfs/models/__init__.py
igelfs/models/abc.py
igelfs/models/base.py
igelfs/models/boot_registry.py
igelfs/models/bootsplash.py
igelfs/models/collections.py
igelfs/models/directory.py
igelfs/models/efs.py
igelfs/models/hash.py
igelfs/models/mixins.py
igelfs/models/partition.py
igelfs/models/section.py
igelfs/tests/conftest.py
igelfs/tests/markers.py
igelfs/tests/test_boot_registry.py
igelfs/tests/test_bootsplash.py
igelfs/tests/test_directory.py
igelfs/tests/test_filesystem.py
igelfs/tests/test_hash.py
igelfs/tests/test_kml.py
igelfs/tests/test_lxos_parser.py
igelfs/tests/test_models.py
igelfs/tests/test_registry.py
igelfs/tests/test_section.py
igelfs-2.12.0.dist-info/licenses/LICENSE
igelfs-2.12.0.dist-info/METADATA
igelfs-2.12.0.dist-info/WHEEL
igelfs-2.12.0.dist-info/entry_points.txt
igelfs-2.12.0.dist-info/top_level.txt
igelfs-2.12.0.dist-info/RECORD
