Metadata-Version: 2.4
Name: igelfs
Version: 2.12.0
Summary: Python implementation of the IGEL filesystem.
Author: Zack Didcott
Maintainer: Zack Didcott
License-Expression: GPL-3.0-only
Project-URL: Homepage, https://github.com/Zedeldi/igelfs
Project-URL: Documentation, https://github.com/Zedeldi/igelfs/wiki
Project-URL: Repository, https://github.com/Zedeldi/igelfs.git
Project-URL: Issues, https://github.com/Zedeldi/igelfs/issues
Requires-Python: >=3.12
License-File: LICENSE
Requires-Dist: pillow
Requires-Dist: python-magic
Requires-Dist: rsa
Provides-Extra: convert
Requires-Dist: pyparted; extra == "convert"
Provides-Extra: crypto
Requires-Dist: cryptography; extra == "crypto"
Requires-Dist: pycryptodome; extra == "crypto"
Requires-Dist: PyNaCl; extra == "crypto"
Requires-Dist: python-lzf; extra == "crypto"
Provides-Extra: fuse
Requires-Dist: fuse-python; extra == "fuse"
Provides-Extra: tests
Requires-Dist: pytest; extra == "tests"
Dynamic: license-file
